[{"text": "وَضْعُ", "offset": 104.25, "duration": 352.666}, {"text": "النَّظَّارَةِ", "offset": 470.5, "duration": 651.125}, {"text": "الشَّمْسِيَّةِ", "offset": 1135.166, "duration": 732.5}, {"text": "فِي", "offset": 1881.25, "duration": 81.375}, {"text": "الشَّمْسِ", "offset": 1976.208, "duration": 651.125}, {"text": "تَصَرُّفٌ", "offset": 2871.5, "duration": 678.25}, {"text": "مُفِيدٌ", "offset": 3563.291, "duration": 488.333}, {"text": "أَمْ", "offset": 4065.208, "duration": 162.791}, {"text": "ضَارٌّ", "offset": 4241.541, "duration": 529.041}]