[
  {
    "text": "اليَوْمَ",
    "offset": 104,
    "duration": 529
  },
  {
    "text": "نَكْتَشِفُ",
    "offset": 646,
    "duration": 569
  },
  {
    "text": "حَوَاسَّنَا",
    "offset": 1230,
    "duration": 529
  },
  {
    "text": "الخَمْسَ",
    "offset": 1772,
    "duration": 488
  },
  {
    "text": "فِي",
    "offset": 2274,
    "duration": 176
  },
  {
    "text": "حَظِيرَةِ",
    "offset": 2464,
    "duration": 569
  },
  {
    "text": "القَالَة",
    "offset": 3047,
    "duration": 678
  }
]